garpix_company/CHANGELOG.md
garpix_company/CONTRIBUTING.md
garpix_company/MANIFEST.in
garpix_company/README.md
garpix_company/__init__.py
garpix_company/apps.py
garpix_company/helpers.py
garpix_company/settings.py
garpix_company/setup.py
garpix_company/tests.py
garpix_company/urls.py
garpix_company/admin/__init__.py
garpix_company/admin/company.py
garpix_company/admin/company_invite.py
garpix_company/managers/__init__.py
garpix_company/managers/company.py
garpix_company/managers/invite.py
garpix_company/migrations/__init__.py
garpix_company/mixins/__init__.py
garpix_company/mixins/views/__init__.py
garpix_company/mixins/views/company_mixin.py
garpix_company/models/__init__.py
garpix_company/models/company.py
garpix_company/models/invite.py
garpix_company/models/user_company.py
garpix_company/models/user_role.py
garpix_company/permissions/__init__.py
garpix_company/permissions/company_admin.py
garpix_company/permissions/company_owner.py
garpix_company/permissions/company_user.py
garpix_company/permissions/invite_receiver.py
garpix_company/serializers/__init__.py
garpix_company/serializers/company.py
garpix_company/serializers/invite.py
garpix_company/serializers/role.py
garpix_company/serializers/user.py
garpix_company/serializers/user_company.py
garpix_company/services/__init__.py
garpix_company/services/role_service.py
garpix_company/views/__init__.py
garpix_company/views/company.py
garpix_company/views/invite.py
garpix_company/views/user_company.py
garpix_company-2.8.3.dist-info/METADATA
garpix_company-2.8.3.dist-info/WHEEL
garpix_company-2.8.3.dist-info/top_level.txt
garpix_company-2.8.3.dist-info/RECORD
