Metadata-Version: 2.1
Name: garpix-company
Version: 2.8.3
Home-page: https://github.com/garpixcms/garpix_company
Author: Garpix LTD
Author-email: info@garpix.com
License: MIT
Classifier: Development Status :: 4 - Beta
Classifier: Environment :: Web Environment
Classifier: Intended Audience :: Developers
Classifier: License :: OSI Approved :: MIT License
Classifier: Operating System :: OS Independent
Classifier: Programming Language :: Python
Classifier: Framework :: Django
Classifier: Programming Language :: Python :: 3.8
Requires-Dist: garpixcms (>=3.43.0)
Requires-Dist: drf-nested-routers (==0.93.4)
Requires-Dist: django-fsm (>=2.8.1)
Requires-Dist: django-filter (>=21.1)
